Workbook

Sheet Start Here
A1: Sales Data Analysis — Practice Deliverable
A2: Purpose | B2: Fictional dataset for spreadsheet cleaning, formulas, pivot-style summaries, and charts.
A3: How to use | B3: Review Raw Data first. Raw Data is preserved exactly as generated, including one duplicate and one blank row.
A4: Cleaning log | B4: Removed 1 entirely blank row. Removed duplicate OrderID ORD-1005 (kept first occurrence).
A5: Business key | B5: OrderID is used as the business key because each order should be unique.
A6: Formula — Revenue | B6: Revenue = Quantity × UnitPrice (Excel example: =D2*E2).
A7: Formula — Cost | B7: Cost = Quantity × UnitCost (Excel example: =D2*F2).
A8: Formula — Margin | B8: Margin = Revenue − Cost (Excel example: =G2-D2*F2).
A9: Formula — Margin % | B9: Margin % = Margin / Revenue; formatted as percentage.
A10: Formula — IF | B10: Quantity check: =IF(D2>0,"OK","Check")
A11: Formula — XLOOKUP | B11: =XLOOKUP(C2,Prices!A:A,Prices!B:B,"Unknown") — see Cleaned Data lookup column.
A12: Formula — SUMIFS | B12: =SUMIFS(G:G,B:B,"West") — see Formula Practice sheet.
A13: Pivot note | B13: Pivot Summary and the region/category/month summaries are precomputed summaries from the cleaned dataset for compatibility.
A14: Reconciliation | B14: Cleaned total revenue = ₹963,600; region/category/month summary revenue totals reconcile to this amount.
A15: Dataset note | B15: All orders, prices, costs, regions, and products are fictional and intended for practice only.
A16: Next step | B16: Open the Pivot Summary and Charts sheets. For a live Excel PivotTable, select Cleaned Data and use Insert > PivotTable.

Sheet Raw Data
A1: Date | B1: Region | C1: Category | D1: Quantity | E1: UnitPrice | F1: UnitCost | G1: OrderID
A2: 46027 | B2: West | C2: Laptop | D2: 2 | E2: 55000 | F2: 42000 | G2: ORD-1001
A3: 46034 | B3: North | C3: Phone | D3: 5 | E3: 18000 | F3: 12500 | G3: ORD-1002
A4: 46042 | B4: South | C4: Tablet | D4: 3 | E4: 22000 | F4: 16000 | G4: ORD-1003
A5: 46056 | B5: East | C5: Laptop | D5: 1 | E5: 56000 | F5: 42500 | G5: ORD-1004
A6: 46067 | B6: West | C6: Phone | D6: 4 | E6: 17500 | F6: 12200 | G6: ORD-1005
A7: 46077 | B7: North | C7: Tablet | D7: 2 | E7: 22500 | F7: 16200 | G7: ORD-1006
A8: 46083 | B8: South | C8: Laptop | D8: 2 | E8: 54500 | F8: 41500 | G8: ORD-1007
A9: 46091 | B9: East | C9: Phone | D9: 6 | E9: 18200 | F9: 12600 | G9: ORD-1008
A10: 46099 | B10: West | C10: Tablet | D10: 4 | E10: 21800 | F10: 15800 | G10: ORD-1009
A11: 46113 | B11: North | C11: Laptop | D11: 1 | E11: 57000 | F11: 43000 | G11: ORD-1010
A12: 46123 | B12: South | C12: Phone | D12: 3 | E12: 17900 | F12: 12400 | G12: ORD-1011
A13: 46134 | B13: East | C13: Tablet | D13: 5 | E13: 22100 | F13: 16100 | G13: ORD-1012
A14: 46067 | B14: West | C14: Phone | D14: 4 | E14: 17500 | F14: 12200 | G14: ORD-1005

Sheet Cleaned Data
A1: Date | B1: Region | C1: Category | D1: Quantity | E1: UnitPrice | F1: UnitCost | G1: OrderID | H1: Revenue | I1: Cost | J1: Margin | K1: MarginPct | L1: QuantityCheck | M1: LookupPrice | N1: Month
A2: 46027 | B2: West | C2: Laptop | D2: 2 | E2: 55000 | F2: 42000 | G2: ORD-1001 | H2: =E2*D2 | I2: =F2*D2 | J2: =H2-I2 | K2: =IF(H2=0,0,J2/H2) | L2: =IF(D2>0,"OK","Check") | M2: =XLOOKUP(C2,Prices!A:A,Prices!B:B,"Unknown") | N2: =TEXT(A2,"yyyy-mm")
A3: 46034 | B3: North | C3: Phone | D3: 5 | E3: 18000 | F3: 12500 | G3: ORD-1002 | H3: =E3*D3 | I3: =F3*D3 | J3: =H3-I3 | K3: =IF(H3=0,0,J3/H3) | L3: =IF(D3>0,"OK","Check") | M3: =XLOOKUP(C3,Prices!A:A,Prices!B:B,"Unknown") | N3: =TEXT(A3,"yyyy-mm")
A4: 46042 | B4: South | C4: Tablet | D4: 3 | E4: 22000 | F4: 16000 | G4: ORD-1003 | H4: =E4*D4 | I4: =F4*D4 | J4: =H4-I4 | K4: =IF(H4=0,0,J4/H4) | L4: =IF(D4>0,"OK","Check") | M4: =XLOOKUP(C4,Prices!A:A,Prices!B:B,"Unknown") | N4: =TEXT(A4,"yyyy-mm")
A5: 46056 | B5: East | C5: Laptop | D5: 1 | E5: 56000 | F5: 42500 | G5: ORD-1004 | H5: =E5*D5 | I5: =F5*D5 | J5: =H5-I5 | K5: =IF(H5=0,0,J5/H5) | L5: =IF(D5>0,"OK","Check") | M5: =XLOOKUP(C5,Prices!A:A,Prices!B:B,"Unknown") | N5: =TEXT(A5,"yyyy-mm")
A6: 46067 | B6: West | C6: Phone | D6: 4 | E6: 17500 | F6: 12200 | G6: ORD-1005 | H6: =E6*D6 | I6: =F6*D6 | J6: =H6-I6 | K6: =IF(H6=0,0,J6/H6) | L6: =IF(D6>0,"OK","Check") | M6: =XLOOKUP(C6,Prices!A:A,Prices!B:B,"Unknown") | N6: =TEXT(A6,"yyyy-mm")
A7: 46077 | B7: North | C7: Tablet | D7: 2 | E7: 22500 | F7: 16200 | G7: ORD-1006 | H7: =E7*D7 | I7: =F7*D7 | J7: =H7-I7 | K7: =IF(H7=0,0,J7/H7) | L7: =IF(D7>0,"OK","Check") | M7: =XLOOKUP(C7,Prices!A:A,Prices!B:B,"Unknown") | N7: =TEXT(A7,"yyyy-mm")
A8: 46083 | B8: South | C8: Laptop | D8: 2 | E8: 54500 | F8: 41500 | G8: ORD-1007 | H8: =E8*D8 | I8: =F8*D8 | J8: =H8-I8 | K8: =IF(H8=0,0,J8/H8) | L8: =IF(D8>0,"OK","Check") | M8: =XLOOKUP(C8,Prices!A:A,Prices!B:B,"Unknown") | N8: =TEXT(A8,"yyyy-mm")
A9: 46091 | B9: East | C9: Phone | D9: 6 | E9: 18200 | F9: 12600 | G9: ORD-1008 | H9: =E9*D9 | I9: =F9*D9 | J9: =H9-I9 | K9: =IF(H9=0,0,J9/H9) | L9: =IF(D9>0,"OK","Check") | M9: =XLOOKUP(C9,Prices!A:A,Prices!B:B,"Unknown") | N9: =TEXT(A9,"yyyy-mm")
A10: 46099 | B10: West | C10: Tablet | D10: 4 | E10: 21800 | F10: 15800 | G10: ORD-1009 | H10: =E10*D10 | I10: =F10*D10 | J10: =H10-I10 | K10: =IF(H10=0,0,J10/H10) | L10: =IF(D10>0,"OK","Check") | M10: =XLOOKUP(C10,Prices!A:A,Prices!B:B,"Unknown") | N10: =TEXT(A10,"yyyy-mm")
A11: 46113 | B11: North | C11: Laptop | D11: 1 | E11: 57000 | F11: 43000 | G11: ORD-1010 | H11: =E11*D11 | I11: =F11*D11 | J11: =H11-I11 | K11: =IF(H11=0,0,J11/H11) | L11: =IF(D11>0,"OK","Check") | M11: =XLOOKUP(C11,Prices!A:A,Prices!B:B,"Unknown") | N11: =TEXT(A11,"yyyy-mm")
A12: 46123 | B12: South | C12: Phone | D12: 3 | E12: 17900 | F12: 12400 | G12: ORD-1011 | H12: =E12*D12 | I12: =F12*D12 | J12: =H12-I12 | K12: =IF(H12=0,0,J12/H12) | L12: =IF(D12>0,"OK","Check") | M12: =XLOOKUP(C12,Prices!A:A,Prices!B:B,"Unknown") | N12: =TEXT(A12,"yyyy-mm")
A13: 46134 | B13: East | C13: Tablet | D13: 5 | E13: 22100 | F13: 16100 | G13: ORD-1012 | H13: =E13*D13 | I13: =F13*D13 | J13: =H13-I13 | K13: =IF(H13=0,0,J13/H13) | L13: =IF(D13>0,"OK","Check") | M13: =XLOOKUP(C13,Prices!A:A,Prices!B:B,"Unknown") | N13: =TEXT(A13,"yyyy-mm")

Sheet Prices
A1: Category | B1: ReferencePrice
A2: Laptop | B2: 55000
A3: Phone | B3: 18000
A4: Tablet | B4: 22000

Sheet Formula Practice
A1: Formula Practice | B1: Example / Expected result
A2: West regional revenue | B2: =SUMIFS('Cleaned Data'!H:H,'Cleaned Data'!B:B,"West")
A3: Quantity validation | B3: =IF('Cleaned Data'!D2>0,"OK","Check")
A4: Lookup example | B4: =XLOOKUP('Cleaned Data'!C2,Prices!A:A,Prices!B:B,"Unknown")
A5: VLOOKUP alternative | B5: =VLOOKUP('Cleaned Data'!C2,Prices!A:B,2,FALSE)
A6: Manual check 1 | B6: ORD-1001: 2 × ₹55,000 = ₹110,000 revenue; margin = 2 × (₹55,000 − ₹42,000) = ₹26,000.
A7: Manual check 2 | B7: ORD-1005: 4 × ₹17,500 = ₹70,000 revenue; margin = 4 × (₹17,500 − ₹12,200) = ₹21,200.

Sheet Pivot Summary
A1: Region | B1: Category | C1: Total Revenue | D1: Total Units
A2: East | B2: Laptop | C2: 56000 | D2: 1
A3: East | B3: Phone | C3: 109200 | D3: 6
A4: East | B4: Tablet | C4: 110500 | D4: 5
A5: North | B5: Laptop | C5: 57000 | D5: 1
A6: North | B6: Phone | C6: 90000 | D6: 5
A7: North | B7: Tablet | C7: 45000 | D7: 2
A8: South | B8: Laptop | C8: 109000 | D8: 2
A9: South | B9: Phone | C9: 53700 | D9: 3
A10: South | B10: Tablet | C10: 66000 | D10: 3
A11: West | B11: Laptop | C11: 110000 | D11: 2
A12: West | B12: Phone | C12: 70000 | D12: 4
A13: West | B13: Tablet | C13: 87200 | D13: 4
A15: Region Summary
A16: Region | B16: Total Revenue | C16: Total Units
A17: East | B17: 275700 | C17: 12
A18: North | B18: 192000 | C18: 8
A19: South | B19: 228700 | C19: 8
A20: West | B20: 267200 | C20: 10
A22: Category Summary
A23: Category | B23: Total Revenue | C23: Total Units
A24: Laptop | B24: 332000 | C24: 6
A25: Phone | B25: 322900 | C25: 18
A26: Tablet | B26: 308700 | C26: 14
A28: Monthly Summary
A29: Month | B29: Total Revenue | C29: Total Units
A30: 2026-01 | B30: 266000 | C30: 10
A31: 2026-02 | B31: 171000 | C31: 7
A32: 2026-03 | B32: 305400 | C32: 12
A33: 2026-04 | B33: 221200 | C33: 9

Sheet Charts
A1: Sales Visualizations
A2: Category revenue bar chart and monthly revenue trend chart are embedded below.

Sheet Observations
A1: Observation | B1: Evidence
A2: Laptop is the highest-revenue category. | B2: Revenue = ₹332,000.
A3: March 2026 is the strongest month in the sample. | B3: Revenue = ₹305,400.
A4: East is the highest-revenue region. | B4: Revenue = ₹275,700.
A5: Caution | B5: This is a small fictional practice dataset; findings are only for demonstrating analysis, not real business decisions.
